pytest_jsonreport/__init__.py
pytest_jsonreport/plugin.py
pytest_jsonreport/serialize.py
pytest_json_report_wip-1.5.1.dist-info/LICENSE
pytest_json_report_wip-1.5.1.dist-info/METADATA
pytest_json_report_wip-1.5.1.dist-info/WHEEL
pytest_json_report_wip-1.5.1.dist-info/entry_points.txt
pytest_json_report_wip-1.5.1.dist-info/top_level.txt
pytest_json_report_wip-1.5.1.dist-info/RECORD
