Metadata-Version: 2.1
Name: pytest-json-report-wip
Version: 1.5.1
Summary: A pytest plugin to report test results as JSON files
Home-page: https://github.com/numirias/pytest-json-report
Author: numirias
Author-email: numirias@users.noreply.github.com
License: MIT
Classifier: Development Status :: 4 - Beta
Classifier: Programming Language :: Python
Classifier: Programming Language :: Python :: 3
Classifier: Programming Language :: Python :: 3.8
Classifier: Programming Language :: Python :: 3.9
Classifier: Programming Language :: Python :: 3.10
Classifier: Programming Language :: Python :: 3.11
Classifier: Programming Language :: Python :: 3.12
Classifier: Framework :: Pytest
License-File: LICENSE
Requires-Dist: pytest >=3.8.0
Requires-Dist: pytest-metadata >=3.0.0
